<annotation>
	<folder></folder>
	<filename>Bed-Bug-57_png.rf.bd758799988301681e1e169cc2b36568.jpg</filename>
	<path>Bed-Bug-57_png.rf.bd758799988301681e1e169cc2b36568.jpg</path>
	<source>
		<database>roboflow.com</database>
	</source>
	<size>
		<width>640</width>
		<height>640</height>
		<depth>3</depth>
	</size>
	<segmented>0</segmented>
	<object>
		<name>kan emici bocekler</name>
		<pose>Unspecified</pose>
		<truncated>0</truncated>
		<difficult>0</difficult>
		<occluded>0</occluded>
		<bndbox>
			<xmin>151</xmin>
			<xmax>267</xmax>
			<ymin>252</ymin>
			<ymax>358</ymax>
		</bndbox>
	</object>
	<object>
		<name>kan emici bocekler</name>
		<pose>Unspecified</pose>
		<truncated>0</truncated>
		<difficult>0</difficult>
		<occluded>0</occluded>
		<bndbox>
			<xmin>273</xmin>
			<xmax>366</xmax>
			<ymin>247</ymin>
			<ymax>319</ymax>
		</bndbox>
	</object>
	<object>
		<name>kan emici bocekler</name>
		<pose>Unspecified</pose>
		<truncated>0</truncated>
		<difficult>0</difficult>
		<occluded>0</occluded>
		<bndbox>
			<xmin>390</xmin>
			<xmax>485</xmax>
			<ymin>137</ymin>
			<ymax>220</ymax>
		</bndbox>
	</object>
	<object>
		<name>kan emici bocekler</name>
		<pose>Unspecified</pose>
		<truncated>0</truncated>
		<difficult>0</difficult>
		<occluded>0</occluded>
		<bndbox>
			<xmin>536</xmin>
			<xmax>638</xmax>
			<ymin>81</ymin>
			<ymax>172</ymax>
		</bndbox>
	</object>
	<object>
		<name>kan emici bocekler</name>
		<pose>Unspecified</pose>
		<truncated>0</truncated>
		<difficult>0</difficult>
		<occluded>0</occluded>
		<bndbox>
			<xmin>195</xmin>
			<xmax>330</xmax>
			<ymin>425</ymin>
			<ymax>524</ymax>
		</bndbox>
	</object>
</annotation>
